sword2vec/__init__.py
sword2vec/helpers.cp310-win_amd64.pyd
sword2vec/preprocessor.py
sword2vec/word2vec.py
sword2vec-3.4.7.dist-info/LICENSE
sword2vec-3.4.7.dist-info/METADATA
sword2vec-3.4.7.dist-info/WHEEL
sword2vec-3.4.7.dist-info/top_level.txt
sword2vec-3.4.7.dist-info/RECORD
